{
  "authors": [
    {
      "name": "0728a400aa1c86fe"
    }
  ],
  "bib_ref": "cm:29db2248aba45e59:a4a999ee55bd1f5b",
  "local_bib": "doc.bib",
  "local_doc": "doc.pdf",
  "place": "",
  "publish_iso_date": "2021-03-30",
  "reproducible": "yes",
  "title": "Collective Knowledge: organizing research projects as a database of reusable components and portable workflows with common APIs",
  "urls": [
    {
      "title": "DOI", 
      "url": "https://doi.org/10.1098/rsta.2020.0211"
    },
    {
      "title": "preprint", 
      "url": "https://arxiv.org/abs/2011.01149"
    }
  ],
  "type": {
    "name": "journal",
    "peer_reviewed": "yes",
    "scope": "international"
  },
  "when": "March 2021",
  "where": "Accepted for Philosophical Transactions A of the Royal Society"
}
