{
  "backup_data_uid": "04f8c9ac1e0042c7", 
  "backup_module_uid": "58014c9c91d6d101", 
  "backup_module_uoa": "class", 
  "cm_outdated": {
    "cm_access_control": {
      "comments_groups": "registered", 
      "read_groups": "all", 
      "write_groups": "owner"
    }, 
    "powered_by": {
      "name": "Collective Mind Engine", 
      "version": "1.0.3121.beta"
    }
  }, 
  "control": {
    "author_uoa": "0728a400aa1c86fe", 
    "engine": "CM", 
    "iso_datetime": "2014-08-05T12:31:23.320000", 
    "version": []
  }, 
  "data_name": "compiler.gcc.4.8.3"
}
