{
  "abbreviation": "", 
  "cm_access_control": {
    "comments_groups": "registered", 
    "read_groups": "registered", 
    "write_groups": "owner"
  }, 
  "cm_classes_uoa": [], 
  "cm_dependencies": {
    "classes": []
  }, 
  "cm_description": "University of Pittsburgh", 
  "cm_display_as_alias": "University of Pittsburgh, USA", 
  "cm_dissemination": {}, 
  "cm_properties": {}, 
  "cm_updated": [
    {
      "cm_iso_datetime": "2013-11-24T17:30:28.540000", 
      "cm_module_uid": "3594786b07dc710d", 
      "cm_person_uoa": "0728a400aa1c86fe", 
      "cm_user_uoa": "0728a400aa1c86fe"
    }
  ], 
  "country": "", 
  "name": "", 
  "powered_by": {
    "name": "Collective Mind Engine", 
    "version": "1.0.2318.beta"
  }, 
  "type": "", 
  "urls": []
}
